{
  "id": "6733375d481906a53",
  "name": "SHAH KANIZ FATIMA ASIF ALI SULTANA BEGUM from C.E.S. Michael High School, Kurla",
  "surname": "SHAH",
  "firstName": "KANIZ FATIMA",
  "fathersName": "ASIF ALI",
  "mothersName": "SULTANA BEGUM",
  "standard": "1",
  "medium": "English",
  "gender": "Female",
  "code": "1E1305020054",
  "barcode": "1E1305020054",
  "score": "28",
  "rank": "",
  "remarks": "FAIL",
  "schoolName": "C.E.S. Michael High School, Kurla",
  "score11": "28",
  "score12": "0",
  "score21": "",
  "score22": "",
  "remarks11": "FAIL",
  "remarks12": "FAIL",
  "remarks21": "",
  "remarks22": "",
  "status": "CHECKED",
  "rankSeq": "0",
  "award": "",
  "examCentreName": "C.E.S. Michael High School, Kurla"
}