{
  "id": "672c627547e424025",
  "name": "RATHOD HARSHITA VISHNU SAVITA from Century Rayon Primary School, Shahad",
  "surname": "RATHOD",
  "firstName": "HARSHITA",
  "fathersName": "VISHNU",
  "mothersName": "SAVITA",
  "standard": "1",
  "medium": "English",
  "gender": "Female",
  "code": "1E1515010042",
  "barcode": "1E1515010042",
  "score": "16",
  "rank": "",
  "remarks": "FAIL",
  "schoolName": "Century Rayon Primary School, Shahad",
  "score11": "16",
  "score12": "0",
  "score21": "",
  "score22": "",
  "remarks11": "FAIL",
  "remarks12": "FAIL",
  "remarks21": "",
  "remarks22": "",
  "status": "CHECKED",
  "rankSeq": "0",
  "award": "",
  "examCentreName": "Century Rayon Primary School, Shahad"
}