{
  "id": "673ed37fe3b688f53",
  "name": "KAMBLI RUVANSHI SUNIL SEEMA from Yogi Shri Arvind Gurukul Eng. Med. School, Badlapur",
  "surname": "KAMBLI",
  "firstName": "RUVANSHI",
  "fathersName": "SUNIL",
  "mothersName": "SEEMA",
  "standard": "1",
  "medium": "English",
  "gender": "Female",
  "code": "1E1501020012",
  "barcode": "1E1501020012",
  "score": "24",
  "rank": "",
  "remarks": "FAIL",
  "schoolName": "Yogi Shri Arvind Gurukul Eng. Med. School, Badlapur",
  "score11": "24",
  "score12": "0",
  "score21": "",
  "score22": "",
  "remarks11": "FAIL",
  "remarks12": "FAIL",
  "remarks21": "",
  "remarks22": "",
  "status": "CHECKED",
  "rankSeq": "0",
  "award": "",
  "examCentreName": "Panna English High School, Badlapur"
}