{
  "id": "6728cec3dd6e947e6",
  "name": "NASARDI ARFA PARVEZ FARHEEN from Anna Bhau English School, Ajara",
  "surname": "NASARDI",
  "firstName": "ARFA",
  "fathersName": "PARVEZ",
  "mothersName": "FARHEEN",
  "standard": "1",
  "medium": "English",
  "gender": "Female",
  "code": "1E4102010008",
  "barcode": "1E4102010008",
  "score": "34",
  "rank": "",
  "remarks": "PASS",
  "schoolName": "Anna Bhau English School, Ajara",
  "score11": "34",
  "score12": "0",
  "score21": "",
  "score22": "",
  "remarks11": "PASS",
  "remarks12": "FAIL",
  "remarks21": "",
  "remarks22": "",
  "status": "CHECKED",
  "rankSeq": "0",
  "award": "",
  "examCentreName": "Vyankatrao High School, Ajara"
}