{
  "id": "672c627db3bdc1641",
  "name": "SUTAR VRUSHBH BABU SUPRIYA from Mohite Patil Vidyalay, Mankhurd",
  "surname": "SUTAR",
  "firstName": "VRUSHBH",
  "fathersName": "BABU",
  "mothersName": "SUPRIYA",
  "standard": "1",
  "medium": "Semi",
  "gender": "Male",
  "code": "1S1309010063",
  "barcode": "1S1309010063",
  "score": "42",
  "rank": "",
  "remarks": "PASS",
  "schoolName": "Mohite Patil Vidyalay, Mankhurd",
  "score11": "42",
  "score12": "0",
  "score21": "",
  "score22": "",
  "remarks11": "PASS",
  "remarks12": "FAIL",
  "remarks21": "",
  "remarks22": "",
  "status": "CHECKED",
  "rankSeq": "0",
  "award": "",
  "examCentreName": "Mohite Patil Vidyalay, Mankhurd"
}