{
  "id": "672c6279da6d3e8b2",
  "name": "TILWE TANISHKA HARESH SMRUTI from Smt. Vidyaben D. Gardi High School, Mulund",
  "surname": "TILWE",
  "firstName": "TANISHKA",
  "fathersName": "HARESH",
  "mothersName": "SMRUTI",
  "standard": "2",
  "medium": "English",
  "gender": "Female",
  "code": "2E1301010083",
  "barcode": "2E1301010083",
  "score": "42",
  "rank": "",
  "remarks": "PASS",
  "schoolName": "Smt. Vidyaben D. Gardi High School, Mulund",
  "score11": "42",
  "score12": "0",
  "score21": "",
  "score22": "",
  "remarks11": "PASS",
  "remarks12": "FAIL",
  "remarks21": "",
  "remarks22": "",
  "status": "CHECKED",
  "rankSeq": "0",
  "award": "",
  "examCentreName": "Sou. Laxmibai English School & Jr. College, Mulund"
}