{
  "id": "6733376651b0b36fc",
  "name": "BETKAR ANVI RAJESH RIDDHI from Karmaveer Bhaurao Patil English School, Sion",
  "surname": "BETKAR",
  "firstName": "ANVI",
  "fathersName": "RAJESH",
  "mothersName": "RIDDHI",
  "standard": "2",
  "medium": "English",
  "gender": "Female",
  "code": "2E1306010001",
  "barcode": "2E1306010001",
  "score": "36",
  "rank": "",
  "remarks": "PASS",
  "schoolName": "Karmaveer Bhaurao Patil English School, Sion",
  "score11": "36",
  "score12": "0",
  "score21": "",
  "score22": "",
  "remarks11": "PASS",
  "remarks12": "FAIL",
  "remarks21": "",
  "remarks22": "",
  "status": "CHECKED",
  "rankSeq": "0",
  "award": "",
  "examCentreName": "Karmaveer Bhaurao Patil Vidyalaya, Sion"
}