{
  "id": "6735e3e01c9f79323",
  "name": "BHANGALE AMOGH KUNDAN SUJATA from Anand Vishwa Gurukul, Thane",
  "surname": "BHANGALE",
  "firstName": "AMOGH",
  "fathersName": "KUNDAN",
  "mothersName": "SUJATA",
  "standard": "2",
  "medium": "English",
  "gender": "Male",
  "code": "2E1505010001",
  "barcode": "2E1505010001",
  "score": "66",
  "rank": "",
  "remarks": "PASS",
  "schoolName": "Anand Vishwa Gurukul, Thane",
  "score11": "66",
  "score12": "0",
  "score21": "",
  "score22": "",
  "remarks11": "PASS",
  "remarks12": "FAIL",
  "remarks21": "",
  "remarks22": "",
  "status": "CHECKED",
  "rankSeq": "0",
  "award": "",
  "examCentreName": "S.B. Firke English Vidyalay, Thane"
}