{
  "id": "673abb1f31af7427e",
  "name": "DHAMBA URVI SWAPNIL MEGHA from GEI's English Medium School, Kalyan",
  "surname": "DHAMBA",
  "firstName": "URVI",
  "fathersName": "SWAPNIL",
  "mothersName": "MEGHA",
  "standard": "2",
  "medium": "English",
  "gender": "Female",
  "code": "2E1502010025",
  "barcode": "2E1502010025",
  "score": "2",
  "rank": "",
  "remarks": "FAIL",
  "schoolName": "GEI's English Medium School, Kalyan",
  "score11": "2",
  "score12": "0",
  "score21": "",
  "score22": "",
  "remarks11": "FAIL",
  "remarks12": "FAIL",
  "remarks21": "",
  "remarks22": "",
  "status": "CHECKED",
  "rankSeq": "0",
  "award": "",
  "examCentreName": "G.E.I's High School, Kalyan"
}