{
  "id": "6728ce6136e2be958",
  "name": "CHORMALE CHAITRALI ARJUN SONALI from Little Angel English Medium School, Vikramgad",
  "surname": "CHORMALE",
  "firstName": "CHAITRALI",
  "fathersName": "ARJUN",
  "mothersName": "SONALI",
  "standard": "2",
  "medium": "English",
  "gender": "Female",
  "code": "2E1602010004",
  "barcode": "2E1602010004",
  "score": "50",
  "rank": "",
  "remarks": "PASS",
  "schoolName": "Little Angel English Medium School, Vikramgad",
  "score11": "50",
  "score12": "0",
  "score21": "",
  "score22": "",
  "remarks11": "PASS",
  "remarks12": "FAIL",
  "remarks21": "",
  "remarks22": "",
  "status": "CHECKED",
  "rankSeq": "0",
  "award": "",
  "examCentreName": "S.B.G.S Vidyalay, Alonde"
}