{
  "id": "673c2ef4448483848",
  "name": "PATIL SHRIVARDHAN YOESH POOJA from Adarsh English Medium School, Wakare",
  "surname": "PATIL",
  "firstName": "SHRIVARDHAN",
  "fathersName": "YOESH",
  "mothersName": "POOJA",
  "standard": "2",
  "medium": "English",
  "gender": "Male",
  "code": "2E4104010019",
  "barcode": "2E4104010019",
  "score": "66",
  "rank": "",
  "remarks": "PASS",
  "schoolName": "Adarsh English Medium School, Wakare",
  "score11": "66",
  "score12": "0",
  "score21": "",
  "score22": "",
  "remarks11": "PASS",
  "remarks12": "FAIL",
  "remarks21": "",
  "remarks22": "",
  "status": "CHECKED",
  "rankSeq": "0",
  "award": "",
  "examCentreName": "Adarsh English Medium School, Wakare"
}