{
  "id": "673ed34f91dfb3c54",
  "name": "RANE NUPUR AMIT VRUSHALI from Parle Tilak Vidyalaya, Vile Parle",
  "surname": "RANE",
  "firstName": "NUPUR",
  "fathersName": "AMIT",
  "mothersName": "VRUSHALI",
  "standard": "2",
  "medium": "Marathi",
  "gender": "Female",
  "code": "2M1201010106",
  "barcode": "2M1201010106",
  "score": "22",
  "rank": "",
  "remarks": "FAIL",
  "schoolName": "Parle Tilak Vidyalaya, Vile Parle",
  "score11": "22",
  "score12": "0",
  "score21": "",
  "score22": "",
  "remarks11": "FAIL",
  "remarks12": "FAIL",
  "remarks21": "",
  "remarks22": "",
  "status": "CHECKED",
  "rankSeq": "0",
  "award": "",
  "examCentreName": "Parle Tilak Vidyalaya, Vile Parle"
}