{
  "id": "672b5078881d6277e",
  "name": "KALE OM NAVNATH POOJA from Sadhana Prarthamik Vidyalay, Hadapsar",
  "surname": "KALE",
  "firstName": "OM",
  "fathersName": "NAVNATH",
  "mothersName": "POOJA",
  "standard": "2",
  "medium": "Marathi",
  "gender": "Male",
  "code": "2M2103010063",
  "barcode": "2M2103010063",
  "score": "78",
  "rank": "",
  "remarks": "PASS",
  "schoolName": "Sadhana Prarthamik Vidyalay, Hadapsar",
  "score11": "78",
  "score12": "0",
  "score21": "",
  "score22": "",
  "remarks11": "PASS",
  "remarks12": "FAIL",
  "remarks21": "",
  "remarks22": "",
  "status": "CHECKED",
  "rankSeq": "0",
  "award": "",
  "examCentreName": "Sadhana Prarthamik Vidyalay, Hadapsar"
}