{
  "id": "6728cec5d071d60aa",
  "name": "BELGUNDKAR SHRISHA AMIT ARATI from Vyankatrao Prathamik Vidya Mandir, Ajara",
  "surname": "BELGUNDKAR",
  "firstName": "SHRISHA",
  "fathersName": "AMIT",
  "mothersName": "ARATI",
  "standard": "2",
  "medium": "Marathi",
  "gender": "Female",
  "code": "2M4102010013",
  "barcode": "2M4102010013",
  "score": "74",
  "rank": "",
  "remarks": "PASS",
  "schoolName": "Vyankatrao Prathamik Vidya Mandir, Ajara",
  "score11": "74",
  "score12": "0",
  "score21": "",
  "score22": "",
  "remarks11": "PASS",
  "remarks12": "FAIL",
  "remarks21": "",
  "remarks22": "",
  "status": "CHECKED",
  "rankSeq": "0",
  "award": "",
  "examCentreName": "Vyankatrao High School, Ajara"
}