{
  "id": "6731d63e6bd9d79db",
  "name": "HIWARLE RUTUJA DEEPAK SONALI from Pratibha Dasharath Bata Prathimik Vidyalaya, Vikhroli",
  "surname": "HIWARLE",
  "firstName": "RUTUJA",
  "fathersName": "DEEPAK",
  "mothersName": "SONALI",
  "standard": "2",
  "medium": "Semi",
  "gender": "Female",
  "code": "2S1303020072",
  "barcode": "2S1303020072",
  "score": "0",
  "rank": "",
  "remarks": "ABSENT",
  "schoolName": "Pratibha Dasharath Bata Prathimik Vidyalaya, Vikhroli",
  "score11": "2",
  "score12": "0",
  "score21": "",
  "score22": "",
  "remarks11": "ABSENT",
  "remarks12": "FAIL",
  "remarks21": "",
  "remarks22": "",
  "status": "CHECKED",
  "rankSeq": "0",
  "award": "",
  "examCentreName": "Kamal Vasudev Vaykole English School, Vikhroli"
}