{
  "id": "673c2f2eef0c22831",
  "name": "MANE AARUSH RAHUL MONICA from S.M.G Vidyamandir, Diva",
  "surname": "MANE",
  "firstName": "AARUSH",
  "fathersName": "RAHUL",
  "mothersName": "MONICA",
  "standard": "2",
  "medium": "Semi",
  "gender": "Male",
  "code": "2S1513010026",
  "barcode": "2S1513010026",
  "score": "74",
  "rank": "",
  "remarks": "PASS",
  "schoolName": "S.M.G Vidyamandir, Diva",
  "score11": "74",
  "score12": "0",
  "score21": "",
  "score22": "",
  "remarks11": "PASS",
  "remarks12": "FAIL",
  "remarks21": "",
  "remarks22": "",
  "status": "CHECKED",
  "rankSeq": "0",
  "award": "",
  "examCentreName": "Shree Ganesh Vidyamandir, Diva"
}