{
  "id": "673ed3887c7d29f5c",
  "name": "KHARATE JIVIKA VIKAS ASHWINI from Ram Bhau Bhise Balvikas Mandir, Nilje Dombivali",
  "surname": "KHARATE",
  "firstName": "JIVIKA",
  "fathersName": "VIKAS",
  "mothersName": "ASHWINI",
  "standard": "2",
  "medium": "Semi",
  "gender": "Female",
  "code": "2S1516010054",
  "barcode": "2S1516010054",
  "score": "14",
  "rank": "",
  "remarks": "FAIL",
  "schoolName": "Ram Bhau Bhise Balvikas Mandir, Nilje Dombivali",
  "score11": "14",
  "score12": "0",
  "score21": "",
  "score22": "",
  "remarks11": "FAIL",
  "remarks12": "FAIL",
  "remarks21": "",
  "remarks22": "",
  "status": "CHECKED",
  "rankSeq": "0",
  "award": "",
  "examCentreName": "Anna Saheb Pawar English School, Kalyan"
}