{
  "id": "672c62775690cec03",
  "name": "KOLI TANAV MANTESH BHAGYASHREE from Maharashtra Mitra Mandal Primary School, Ulhasnagar",
  "surname": "KOLI",
  "firstName": "TANAV",
  "fathersName": "MANTESH",
  "mothersName": "BHAGYASHREE",
  "standard": "2",
  "medium": "Semi",
  "gender": "Male",
  "code": "2S1515010051",
  "barcode": "2S1515010051",
  "score": "16",
  "rank": "",
  "remarks": "FAIL",
  "schoolName": "Maharashtra Mitra Mandal Primary School, Ulhasnagar",
  "score11": "16",
  "score12": "0",
  "score21": "",
  "score22": "",
  "remarks11": "FAIL",
  "remarks12": "FAIL",
  "remarks21": "",
  "remarks22": "",
  "status": "CHECKED",
  "rankSeq": "0",
  "award": "",
  "examCentreName": "Century Rayon Primary School, Shahad"
}