{
  "id": "672b5075823b2f7f2",
  "name": "MORE TANVI VISHWAS PRIYANKA from M.E.S. Bhave Primary School, Pune",
  "surname": "MORE",
  "firstName": "TANVI",
  "fathersName": "VISHWAS",
  "mothersName": "PRIYANKA",
  "standard": "2",
  "medium": "Semi",
  "gender": "Female",
  "code": "2S2101010127",
  "barcode": "2S2101010127",
  "score": "44",
  "rank": "",
  "remarks": "PASS",
  "schoolName": "M.E.S. Bhave Primary School, Pune",
  "score11": "44",
  "score12": "0",
  "score21": "",
  "score22": "",
  "remarks11": "PASS",
  "remarks12": "FAIL",
  "remarks21": "",
  "remarks22": "",
  "status": "CHECKED",
  "rankSeq": "0",
  "award": "",
  "examCentreName": "S.S. Agarwal English Medium School, Pune"
}