{
  "id": "6733376d9ad2cbf5e",
  "name": "KADAM AADHYA PRASHANT PURVI from Ahilya Primary School, Kalachowki",
  "surname": "KADAM",
  "firstName": "AADHYA",
  "fathersName": "PRASHANT",
  "mothersName": "PURVI",
  "standard": "3",
  "medium": "English",
  "gender": "Female",
  "code": "3E1101010026",
  "barcode": "3E1101010026",
  "score": "0",
  "rank": "",
  "remarks": "FAIL",
  "schoolName": "Ahilya Primary School, Kalachowki",
  "score11": "0",
  "score12": "0",
  "score21": "0",
  "score22": "0",
  "remarks11": "FAIL",
  "remarks12": "FAIL",
  "remarks21": "ABSENT",
  "remarks22": "ABSENT",
  "status": "CHECKED",
  "rankSeq": "0",
  "award": "",
  "examCentreName": "K.M.S. English Medium School, Parel"
}