{
  "id": "673abb1828871d459",
  "name": "MOHITE SHRAVAN SANDEEP VIDYA from St. Joseph's High School, Vikhroli",
  "surname": "MOHITE",
  "firstName": "SHRAVAN",
  "fathersName": "SANDEEP",
  "mothersName": "VIDYA",
  "standard": "3",
  "medium": "English",
  "gender": "Male",
  "code": "3E1303010003",
  "barcode": "3E1303010003",
  "score": "210",
  "rank": "",
  "remarks": "PASS",
  "schoolName": "St. Joseph's High School, Vikhroli",
  "score11": "40",
  "score12": "78",
  "score21": "46",
  "score22": "46",
  "remarks11": "PASS",
  "remarks12": "PASS",
  "remarks21": "PASS",
  "remarks22": "PASS",
  "status": "CHECKED",
  "rankSeq": "0",
  "award": "",
  "examCentreName": "Vikas High School Primary Section, Vikhroli"
}