{
  "id": "672c62762658212cf",
  "name": "SUDKU SAMRUDDHI RAKESH SHITAL from Century Rayon Primary School, Shahad",
  "surname": "SUDKU",
  "firstName": "SAMRUDDHI",
  "fathersName": "RAKESH",
  "mothersName": "SHITAL",
  "standard": "3",
  "medium": "English",
  "gender": "Female",
  "code": "3E1515010041",
  "barcode": "3E1515010041",
  "score": "86",
  "rank": "",
  "remarks": "PASS",
  "schoolName": "Century Rayon Primary School, Shahad",
  "score11": "26",
  "score12": "16",
  "score21": "18",
  "score22": "26",
  "remarks11": "PASS",
  "remarks12": "FAIL",
  "remarks21": "PASS",
  "remarks22": "PASS",
  "status": "CHECKED",
  "rankSeq": "0",
  "award": "",
  "examCentreName": "Century Rayon Primary School, Shahad"
}