{
  "id": "673abb1f88e3ce3d5",
  "name": "GAIKWAD PADMAJA SANJAY JYOOTSNA from GEI's English Medium School, Kalyan",
  "surname": "GAIKWAD",
  "firstName": "PADMAJA",
  "fathersName": "SANJAY",
  "mothersName": "JYOOTSNA",
  "standard": "3",
  "medium": "English",
  "gender": "Female",
  "code": "3E1502010024",
  "barcode": "3E1502010024",
  "score": "124",
  "rank": "",
  "remarks": "PASS",
  "schoolName": "GEI's English Medium School, Kalyan",
  "score11": "20",
  "score12": "40",
  "score21": "36",
  "score22": "28",
  "remarks11": "PASS",
  "remarks12": "PASS",
  "remarks21": "PASS",
  "remarks22": "PASS",
  "status": "CHECKED",
  "rankSeq": "0",
  "award": "",
  "examCentreName": "G.E.I's High School, Kalyan"
}