{
  "id": "6731d64a687e16093",
  "name": "PALVE KHUSHI PRAVIN ASHWINI from Cindrella English Medium School, Badlapur",
  "surname": "PALVE",
  "firstName": "KHUSHI",
  "fathersName": "PRAVIN",
  "mothersName": "ASHWINI",
  "standard": "3",
  "medium": "English",
  "gender": "Female",
  "code": "3E1501020051",
  "barcode": "3E1501020051",
  "score": "142",
  "rank": "",
  "remarks": "PASS",
  "schoolName": "Cindrella English Medium School, Badlapur",
  "score11": "30",
  "score12": "42",
  "score21": "36",
  "score22": "34",
  "remarks11": "PASS",
  "remarks12": "PASS",
  "remarks21": "PASS",
  "remarks22": "PASS",
  "status": "CHECKED",
  "rankSeq": "0",
  "award": "",
  "examCentreName": "Panna English High School, Badlapur"
}