{
  "id": "672c62740066f3dc3",
  "name": "TARMALE RUTUJA BALARAM NEERA from Sharada English Medium School, Vasind",
  "surname": "TARMALE",
  "firstName": "RUTUJA",
  "fathersName": "BALARAM",
  "mothersName": "NEERA",
  "standard": "3",
  "medium": "English",
  "gender": "Female",
  "code": "3E1512010066",
  "barcode": "3E1512010066",
  "score": "126",
  "rank": "",
  "remarks": "PASS",
  "schoolName": "Sharada English Medium School, Vasind",
  "score11": "24",
  "score12": "42",
  "score21": "38",
  "score22": "22",
  "remarks11": "PASS",
  "remarks12": "PASS",
  "remarks21": "PASS",
  "remarks22": "FAIL",
  "status": "CHECKED",
  "rankSeq": "0",
  "award": "",
  "examCentreName": "New Ideal School & Jr. College, Vasind"
}