{
  "id": "6728ce6da12a52d0f",
  "name": "SHELORE VISHAKHA VINOD SAPANA from National English School, Kudus",
  "surname": "SHELORE",
  "firstName": "VISHAKHA",
  "fathersName": "VINOD",
  "mothersName": "SAPANA",
  "standard": "3",
  "medium": "English",
  "gender": "Female",
  "code": "3E1604010039",
  "barcode": "3E1604010039",
  "score": "148",
  "rank": "",
  "remarks": "PASS",
  "schoolName": "National English School, Kudus",
  "score11": "34",
  "score12": "34",
  "score21": "34",
  "score22": "46",
  "remarks11": "PASS",
  "remarks12": "PASS",
  "remarks21": "PASS",
  "remarks22": "PASS",
  "status": "CHECKED",
  "rankSeq": "0",
  "award": "",
  "examCentreName": "National English School, Kudus"
}