{
  "id": "6728cec42f404af58",
  "name": "DADDIKAR ADVAIT ABHIJIT TEJASWINI from Anna Bhau English School, Ajara",
  "surname": "DADDIKAR",
  "firstName": "ADVAIT",
  "fathersName": "ABHIJIT",
  "mothersName": "TEJASWINI",
  "standard": "3",
  "medium": "English",
  "gender": "Male",
  "code": "3E4102010004",
  "barcode": "3E4102010004",
  "score": "176",
  "rank": "",
  "remarks": "PASS",
  "schoolName": "Anna Bhau English School, Ajara",
  "score11": "24",
  "score12": "56",
  "score21": "40",
  "score22": "56",
  "remarks11": "PASS",
  "remarks12": "PASS",
  "remarks21": "PASS",
  "remarks22": "PASS",
  "status": "CHECKED",
  "rankSeq": "0",
  "award": "",
  "examCentreName": "Vyankatrao High School, Ajara"
}