{
  "id": "671b46b54d1de056b",
  "name": "ANTULEY ELHAAM KHALID TAHSEEN from Ali Public School, Chiplun",
  "surname": "ANTULEY",
  "firstName": "ELHAAM",
  "fathersName": "KHALID",
  "mothersName": "TAHSEEN",
  "standard": "3",
  "medium": "English",
  "gender": "Female",
  "code": "3E4402020005",
  "barcode": "3E4402020005",
  "score": "162",
  "rank": "",
  "remarks": "PASS",
  "schoolName": "Ali Public School, Chiplun",
  "score11": "32",
  "score12": "50",
  "score21": "32",
  "score22": "48",
  "remarks11": "PASS",
  "remarks12": "PASS",
  "remarks21": "PASS",
  "remarks22": "PASS",
  "status": "CHECKED",
  "rankSeq": "0",
  "award": "",
  "examCentreName": "Christ Jyoti Convent Primary School, Walope"
}