{
  "id": "672b507edbf1bc59b",
  "name": "BELVALKAR SWARAJ SANTOSH VAISHALI from SVJCT's English Medium School, Dervan",
  "surname": "BELVALKAR",
  "firstName": "SWARAJ",
  "fathersName": "SANTOSH",
  "mothersName": "VAISHALI",
  "standard": "3",
  "medium": "English",
  "gender": "Male",
  "code": "3E4401010002",
  "barcode": "3E4401010002",
  "score": "128",
  "rank": "",
  "remarks": "PASS",
  "schoolName": "SVJCT's English Medium School, Dervan",
  "score11": "24",
  "score12": "48",
  "score21": "32",
  "score22": "24",
  "remarks11": "PASS",
  "remarks12": "PASS",
  "remarks21": "PASS",
  "remarks22": "PASS",
  "status": "CHECKED",
  "rankSeq": "0",
  "award": "",
  "examCentreName": "S. V. J. C. T. English Medium School, Dervan"
}