{
  "id": "673c371fe2f04e675",
  "name": "CHOGALE VANSH VINOD VIDHI from S.N.P. School No. 2, Shriwardhan",
  "surname": "CHOGALE",
  "firstName": "VANSH",
  "fathersName": "VINOD",
  "mothersName": "VIDHI",
  "standard": "3",
  "medium": "Marathi",
  "gender": "Male",
  "code": "3M1403010034",
  "barcode": "3M1403010034",
  "score": "146",
  "rank": "",
  "remarks": "PASS",
  "schoolName": "S.N.P. School No. 2, Shriwardhan",
  "score11": "30",
  "score12": "38",
  "score21": "34",
  "score22": "44",
  "remarks11": "PASS",
  "remarks12": "PASS",
  "remarks21": "PASS",
  "remarks22": "PASS",
  "status": "CHECKED",
  "rankSeq": "0",
  "award": "",
  "examCentreName": "R.N. Raut Madhyamik Vidyalaya, Shriwardhan"
}