{
  "id": "6728ce7d7931733cb",
  "name": "NARVEKAR MAHI URMISH SONALI from Utkarsha Vidyalaya, Virar",
  "surname": "NARVEKAR",
  "firstName": "MAHI",
  "fathersName": "URMISH",
  "mothersName": "SONALI",
  "standard": "3",
  "medium": "Marathi",
  "gender": "Female",
  "code": "3M1605010083",
  "barcode": "3M1605010083",
  "score": "152",
  "rank": "",
  "remarks": "PASS",
  "schoolName": "Utkarsha Vidyalaya, Virar",
  "score11": "22",
  "score12": "54",
  "score21": "34",
  "score22": "42",
  "remarks11": "PASS",
  "remarks12": "PASS",
  "remarks21": "PASS",
  "remarks22": "PASS",
  "status": "CHECKED",
  "rankSeq": "0",
  "award": "",
  "examCentreName": "Utkarsha Vidyalaya, Virar"
}