{
  "id": "6728ce7cd9080cb1a",
  "name": "MORE ARNAV VIJAY KIRAN from Utkarsha Vidyalaya, Virar",
  "surname": "MORE",
  "firstName": "ARNAV",
  "fathersName": "VIJAY",
  "mothersName": "KIRAN",
  "standard": "3",
  "medium": "Marathi",
  "gender": "Male",
  "code": "3M1605010079",
  "barcode": "3M1605010079",
  "score": "170",
  "rank": "",
  "remarks": "PASS",
  "schoolName": "Utkarsha Vidyalaya, Virar",
  "score11": "16",
  "score12": "54",
  "score21": "36",
  "score22": "64",
  "remarks11": "PASS",
  "remarks12": "PASS",
  "remarks21": "PASS",
  "remarks22": "PASS",
  "status": "CHECKED",
  "rankSeq": "0",
  "award": "",
  "examCentreName": "Utkarsha Vidyalaya, Virar"
}