{
  "id": "672b5079e58ce8bdb",
  "name": "NANAWARE VIRAJ SUHAS LAXMI from Sadhana Prarthamik Vidyalay, Hadapsar",
  "surname": "NANAWARE",
  "firstName": "VIRAJ",
  "fathersName": "SUHAS",
  "mothersName": "LAXMI",
  "standard": "3",
  "medium": "Marathi",
  "gender": "Male",
  "code": "3M2103010073",
  "barcode": "3M2103010073",
  "score": "94",
  "rank": "",
  "remarks": "PASS",
  "schoolName": "Sadhana Prarthamik Vidyalay, Hadapsar",
  "score11": "12",
  "score12": "30",
  "score21": "24",
  "score22": "28",
  "remarks11": "PASS",
  "remarks12": "PASS",
  "remarks21": "PASS",
  "remarks22": "PASS",
  "status": "CHECKED",
  "rankSeq": "0",
  "award": "",
  "examCentreName": "Sadhana Prarthamik Vidyalay, Hadapsar"
}