{
  "id": "6728ceace26d9c574",
  "name": "VADAR RANVEER HANMANT SAYALI from Central Primay School No. 51, Kasaba Nool",
  "surname": "VADAR",
  "firstName": "RANVEER",
  "fathersName": "HANMANT",
  "mothersName": "SAYALI",
  "standard": "3",
  "medium": "Marathi",
  "gender": "Male",
  "code": "3M4101020228",
  "barcode": "3M4101020228",
  "score": "104",
  "rank": "",
  "remarks": "PASS",
  "schoolName": "Central Primay School No. 51, Kasaba Nool",
  "score11": "24",
  "score12": "32",
  "score21": "22",
  "score22": "26",
  "remarks11": "PASS",
  "remarks12": "PASS",
  "remarks21": "PASS",
  "remarks22": "PASS",
  "status": "CHECKED",
  "rankSeq": "0",
  "award": "",
  "examCentreName": "Shivraj College (Ground Floor), Gadhinglaj"
}