{
  "id": "6728ceb63943e7195",
  "name": "MANGALE ARUSH ASHOK SHUBHANGI from Vidya Mandir, Ainapur",
  "surname": "MANGALE",
  "firstName": "ARUSH",
  "fathersName": "ASHOK",
  "mothersName": "SHUBHANGI",
  "standard": "3",
  "medium": "Marathi",
  "gender": "Male",
  "code": "3M4101020129",
  "barcode": "3M4101020129",
  "score": "164",
  "rank": "",
  "remarks": "PASS",
  "schoolName": "Vidya Mandir, Ainapur",
  "score11": "24",
  "score12": "70",
  "score21": "30",
  "score22": "40",
  "remarks11": "PASS",
  "remarks12": "PASS",
  "remarks21": "PASS",
  "remarks22": "PASS",
  "status": "CHECKED",
  "rankSeq": "0",
  "award": "",
  "examCentreName": "Shivraj College (Ground Floor), Gadhinglaj"
}