{
  "id": "672c6270846105bb1",
  "name": "YADAV AAYUSH KABIR KALPANA from Sudha Mohan Vernekar Primary School, Chembur",
  "surname": "YADAV",
  "firstName": "AAYUSH",
  "fathersName": "KABIR",
  "mothersName": "KALPANA",
  "standard": "3",
  "medium": "Semi",
  "gender": "Male",
  "code": "3S1307010080",
  "barcode": "3S1307010080",
  "score": "114",
  "rank": "",
  "remarks": "PASS",
  "schoolName": "Sudha Mohan Vernekar Primary School, Chembur",
  "score11": "24",
  "score12": "36",
  "score21": "26",
  "score22": "28",
  "remarks11": "PASS",
  "remarks12": "PASS",
  "remarks21": "PASS",
  "remarks22": "PASS",
  "status": "CHECKED",
  "rankSeq": "0",
  "award": "",
  "examCentreName": "Sudha Mohan Vernekar Primary School, Chembur"
}