{
  "id": "673abb1de05f97499",
  "name": "KULKARNI RUJUTA KAUSTUBH HARSHA from GEI's C.M. Puranik Primary School, Kalyan",
  "surname": "KULKARNI",
  "firstName": "RUJUTA",
  "fathersName": "KAUSTUBH",
  "mothersName": "HARSHA",
  "standard": "3",
  "medium": "Semi",
  "gender": "Female",
  "code": "3S1502020095",
  "barcode": "3S1502020095",
  "score": "114",
  "rank": "",
  "remarks": "PASS",
  "schoolName": "GEI's C.M. Puranik Primary School, Kalyan",
  "score11": "14",
  "score12": "38",
  "score21": "28",
  "score22": "34",
  "remarks11": "PASS",
  "remarks12": "PASS",
  "remarks21": "PASS",
  "remarks22": "PASS",
  "status": "CHECKED",
  "rankSeq": "0",
  "award": "",
  "examCentreName": "GEI's New High School, Kalyan"
}