{
  "id": "673ed3888d5ab79a6",
  "name": "KHARATE AARADHYA VIKAS ASHWINI from Ram Bhau Bhise Balvikas Mandir, Nilje Dombivali",
  "surname": "KHARATE",
  "firstName": "AARADHYA",
  "fathersName": "VIKAS",
  "mothersName": "ASHWINI",
  "standard": "3",
  "medium": "Semi",
  "gender": "Female",
  "code": "3S1516010073",
  "barcode": "3S1516010073",
  "score": "102",
  "rank": "",
  "remarks": "PASS",
  "schoolName": "Ram Bhau Bhise Balvikas Mandir, Nilje Dombivali",
  "score11": "14",
  "score12": "32",
  "score21": "32",
  "score22": "24",
  "remarks11": "PASS",
  "remarks12": "PASS",
  "remarks21": "PASS",
  "remarks22": "PASS",
  "status": "CHECKED",
  "rankSeq": "0",
  "award": "",
  "examCentreName": "Anna Saheb Pawar English School, Kalyan"
}