{
  "id": "673ed37e8f5a205d9",
  "name": "TIWARI YUVRAJ SURYAMANI SANDHYA from Namrata Acharya English School, Shelu",
  "surname": "TIWARI",
  "firstName": "YUVRAJ",
  "fathersName": "SURYAMANI",
  "mothersName": "SANDHYA",
  "standard": "4",
  "medium": "English",
  "gender": "Male",
  "code": "4E1409010029",
  "barcode": "4E1409010029",
  "score": "130",
  "rank": "",
  "remarks": "PASS",
  "schoolName": "Namrata Acharya English School, Shelu",
  "score11": "34",
  "score12": "44",
  "score21": "20",
  "score22": "32",
  "remarks11": "PASS",
  "remarks12": "PASS",
  "remarks21": "PASS",
  "remarks22": "PASS",
  "status": "CHECKED",
  "rankSeq": "0",
  "award": "",
  "examCentreName": "Sharda English School, Diksal"
}