{
  "id": "673ed3741668bda2e",
  "name": "SORATE SHARANYA YOGESH SHITAL from RCT's PMM Rotary School & Jr. College, Ambernath",
  "surname": "SORATE",
  "firstName": "SHARANYA",
  "fathersName": "YOGESH",
  "mothersName": "SHITAL",
  "standard": "4",
  "medium": "English",
  "gender": "Male",
  "code": "4E1511010008",
  "barcode": "4E1511010008",
  "score": "138",
  "rank": "",
  "remarks": "PASS",
  "schoolName": "RCT's PMM Rotary School & Jr. College, Ambernath",
  "score11": "24",
  "score12": "38",
  "score21": "40",
  "score22": "36",
  "remarks11": "PASS",
  "remarks12": "PASS",
  "remarks21": "PASS",
  "remarks22": "PASS",
  "status": "CHECKED",
  "rankSeq": "0",
  "award": "",
  "examCentreName": "Smt. Sushilatai Damle Marathi School, Ambernath"
}