{
  "id": "6735e3dcdd20917c1",
  "name": "YADAV SATYENDRA DURGESH PUSHPA from S.V.P.M. English Primary School, Kalwa",
  "surname": "YADAV",
  "firstName": "SATYENDRA",
  "fathersName": "DURGESH",
  "mothersName": "PUSHPA",
  "standard": "4",
  "medium": "English",
  "gender": "Male",
  "code": "4E1504010020",
  "barcode": "4E1504010020",
  "score": "164",
  "rank": "",
  "remarks": "PASS",
  "schoolName": "S.V.P.M. English Primary School, Kalwa",
  "score11": "42",
  "score12": "42",
  "score21": "36",
  "score22": "44",
  "remarks11": "PASS",
  "remarks12": "PASS",
  "remarks21": "PASS",
  "remarks22": "PASS",
  "status": "CHECKED",
  "rankSeq": "0",
  "award": "",
  "examCentreName": "S.V.P.M. English Primary School, Kalwa"
}