{
  "id": "672c6276b101c7c98",
  "name": "YADAV HIMANSHU SANJEEV MANITA from Century Rayon Primary School, Shahad",
  "surname": "YADAV",
  "firstName": "HIMANSHU",
  "fathersName": "SANJEEV",
  "mothersName": "MANITA",
  "standard": "4",
  "medium": "English",
  "gender": "Male",
  "code": "4E1515010049",
  "barcode": "4E1515010049",
  "score": "144",
  "rank": "",
  "remarks": "PASS",
  "schoolName": "Century Rayon Primary School, Shahad",
  "score11": "32",
  "score12": "38",
  "score21": "20",
  "score22": "54",
  "remarks11": "PASS",
  "remarks12": "PASS",
  "remarks21": "PASS",
  "remarks22": "PASS",
  "status": "CHECKED",
  "rankSeq": "0",
  "award": "",
  "examCentreName": "Century Rayon Primary School, Shahad"
}