{
  "id": "673ed38b965109336",
  "name": "BAGUL PRINCE RAVI BHARATI from Progressive Public School, Nashik",
  "surname": "BAGUL",
  "firstName": "PRINCE",
  "fathersName": "RAVI",
  "mothersName": "BHARATI",
  "standard": "4",
  "medium": "English",
  "gender": "Male",
  "code": "4E3101020004",
  "barcode": "4E3101020004",
  "score": "102",
  "rank": "",
  "remarks": "PASS",
  "schoolName": "Progressive Public School, Nashik",
  "score11": "18",
  "score12": "38",
  "score21": "16",
  "score22": "30",
  "remarks11": "PASS",
  "remarks12": "PASS",
  "remarks21": "PASS",
  "remarks22": "PASS",
  "status": "CHECKED",
  "rankSeq": "0",
  "award": "",
  "examCentreName": "Bluebell Primary School, Nashik"
}