{
  "id": "67333764d0686b7ed",
  "name": "PAWAR ANSHIT SUSHIL PRANALI from Shivaji Shikshan Sanstha Primary Vidyalay, Ghatkopar",
  "surname": "PAWAR",
  "firstName": "ANSHIT",
  "fathersName": "SUSHIL",
  "mothersName": "PRANALI",
  "standard": "4",
  "medium": "Marathi",
  "gender": "Male",
  "code": "4M1304010048",
  "barcode": "4M1304010048",
  "score": "74",
  "rank": "",
  "remarks": "PASS",
  "schoolName": "Shivaji Shikshan Sanstha Primary Vidyalay, Ghatkopar",
  "score11": "16",
  "score12": "20",
  "score21": "10",
  "score22": "28",
  "remarks11": "PASS",
  "remarks12": "FAIL",
  "remarks21": "FAIL",
  "remarks22": "PASS",
  "status": "CHECKED",
  "rankSeq": "0",
  "award": "",
  "examCentreName": "Shivaji Techanical High School, Ghatkopar"
}