{
  "id": "673c372021923fdc0",
  "name": "CHOGALE MANASVI MANGESH SUPRIYA from S.N.P. School No. 2, Shriwardhan",
  "surname": "CHOGALE",
  "firstName": "MANASVI",
  "fathersName": "MANGESH",
  "mothersName": "SUPRIYA",
  "standard": "4",
  "medium": "Marathi",
  "gender": "Female",
  "code": "4M1403010036",
  "barcode": "4M1403010036",
  "score": "100",
  "rank": "",
  "remarks": "PASS",
  "schoolName": "S.N.P. School No. 2, Shriwardhan",
  "score11": "14",
  "score12": "26",
  "score21": "20",
  "score22": "40",
  "remarks11": "PASS",
  "remarks12": "PASS",
  "remarks21": "PASS",
  "remarks22": "PASS",
  "status": "CHECKED",
  "rankSeq": "0",
  "award": "",
  "examCentreName": "R.N. Raut Madhyamik Vidyalaya, Shriwardhan"
}