{
  "id": "673c3723579cd8e65",
  "name": "SATPUTE PRERANA SAMADHAN ARCHANA from Chintamanrao Kelkar Vidyalay Marathi Section, Alibaug",
  "surname": "SATPUTE",
  "firstName": "PRERANA",
  "fathersName": "SAMADHAN",
  "mothersName": "ARCHANA",
  "standard": "4",
  "medium": "Marathi",
  "gender": "Female",
  "code": "4M1405010113",
  "barcode": "4M1405010113",
  "score": "108",
  "rank": "",
  "remarks": "PASS",
  "schoolName": "Chintamanrao Kelkar Vidyalay Marathi Section, Alibaug",
  "score11": "22",
  "score12": "40",
  "score21": "16",
  "score22": "30",
  "remarks11": "PASS",
  "remarks12": "PASS",
  "remarks21": "PASS",
  "remarks22": "PASS",
  "status": "CHECKED",
  "rankSeq": "0",
  "award": "",
  "examCentreName": "Chintamanrao Kelkar Vidyalay Marathi Section, Alibaug"
}