{
  "id": "6734652ac27b19012",
  "name": "SUDE ISHAN SHIVDAS JAYASHRI from Ma. Dadasaheb Dandekar Vidyalaya, Bhiwandi",
  "surname": "SUDE",
  "firstName": "ISHAN",
  "fathersName": "SHIVDAS",
  "mothersName": "JAYASHRI",
  "standard": "4",
  "medium": "Marathi",
  "gender": "Male",
  "code": "4M1509010066",
  "barcode": "4M1509010066",
  "score": "74",
  "rank": "",
  "remarks": "PASS",
  "schoolName": "Ma. Dadasaheb Dandekar Vidyalaya, Bhiwandi",
  "score11": "20",
  "score12": "16",
  "score21": "16",
  "score22": "22",
  "remarks11": "PASS",
  "remarks12": "FAIL",
  "remarks21": "PASS",
  "remarks22": "FAIL",
  "status": "CHECKED",
  "rankSeq": "0",
  "award": "",
  "examCentreName": "GEI'S P.R. Vidyalay, Bhiwandi"
}