{
  "id": "672b5071a8fcb6942",
  "name": "AROTE SWANAND DATTATRAYA RAJSHRI from Atma Malik Prathamik Gurukul, Kokmathan",
  "surname": "AROTE",
  "firstName": "SWANAND",
  "fathersName": "DATTATRAYA",
  "mothersName": "RAJSHRI",
  "standard": "4",
  "medium": "Marathi",
  "gender": "Male",
  "code": "4M2201010001",
  "barcode": "4M2201010001",
  "score": "216",
  "rank": "",
  "remarks": "PASS",
  "schoolName": "Atma Malik Prathamik Gurukul, Kokmathan",
  "score11": "48",
  "score12": "72",
  "score21": "36",
  "score22": "60",
  "remarks11": "PASS",
  "remarks12": "PASS",
  "remarks21": "PASS",
  "remarks22": "PASS",
  "status": "CHECKED",
  "rankSeq": "0",
  "award": "",
  "examCentreName": "Atma Malik Prathamik Gurukul, Kokmathan"
}