{
  "id": "6728ceaf09fc85941",
  "name": "GAIKWAD SANSKRITI MARUTI MANISHA from Jeevan Shikshan Vidya Mandir, Vadarage",
  "surname": "GAIKWAD",
  "firstName": "SANSKRITI",
  "fathersName": "MARUTI",
  "mothersName": "MANISHA",
  "standard": "4",
  "medium": "Marathi",
  "gender": "Female",
  "code": "4M4101020032",
  "barcode": "4M4101020032",
  "score": "148",
  "rank": "",
  "remarks": "PASS",
  "schoolName": "Jeevan Shikshan Vidya Mandir, Vadarage",
  "score11": "22",
  "score12": "52",
  "score21": "32",
  "score22": "42",
  "remarks11": "PASS",
  "remarks12": "PASS",
  "remarks21": "PASS",
  "remarks22": "PASS",
  "status": "CHECKED",
  "rankSeq": "0",
  "award": "",
  "examCentreName": "Shivraj College (Ground Floor), Gadhinglaj"
}