{
  "id": "6728cec6954431701",
  "name": "MANGAONKAR MANTASHA ARIF SALMA from Vyankatrao Prathamik Vidya Mandir, Ajara",
  "surname": "MANGAONKAR",
  "firstName": "MANTASHA",
  "fathersName": "ARIF",
  "mothersName": "SALMA",
  "standard": "4",
  "medium": "Marathi",
  "gender": "Female",
  "code": "4M4102010037",
  "barcode": "4M4102010037",
  "score": "158",
  "rank": "",
  "remarks": "PASS",
  "schoolName": "Vyankatrao Prathamik Vidya Mandir, Ajara",
  "score11": "32",
  "score12": "40",
  "score21": "38",
  "score22": "48",
  "remarks11": "PASS",
  "remarks12": "PASS",
  "remarks21": "PASS",
  "remarks22": "PASS",
  "status": "CHECKED",
  "rankSeq": "0",
  "award": "",
  "examCentreName": "Vyankatrao High School, Ajara"
}