{
  "id": "6733376aeeea01b9b",
  "name": "MHATRE PRANJAL VINOD MANISH from D.D. Alis Babasaheb Deshpande Primary School, Sion",
  "surname": "MHATRE",
  "firstName": "PRANJAL",
  "fathersName": "VINOD",
  "mothersName": "MANISH",
  "standard": "4",
  "medium": "Semi",
  "gender": "Female",
  "code": "4S1306020041",
  "barcode": "4S1306020041",
  "score": "166",
  "rank": "",
  "remarks": "PASS",
  "schoolName": "D.D. Alis Babasaheb Deshpande Primary School, Sion",
  "score11": "34",
  "score12": "42",
  "score21": "36",
  "score22": "54",
  "remarks11": "PASS",
  "remarks12": "PASS",
  "remarks21": "PASS",
  "remarks22": "PASS",
  "status": "CHECKED",
  "rankSeq": "0",
  "award": "",
  "examCentreName": "D.D. Alis Babasaheb Deshpande Primary School, Sion"
}