{
  "id": "673c2f7b1d574f154",
  "name": "BHOSALE SANVI SOMNATH SUPRIYA from Sushma Patil Primary Vidyalaya, Kamothe",
  "surname": "BHOSALE",
  "firstName": "SANVI",
  "fathersName": "SOMNATH",
  "mothersName": "SUPRIYA",
  "standard": "4",
  "medium": "Semi",
  "gender": "Female",
  "code": "4S1412010067",
  "barcode": "4S1412010067",
  "score": "160",
  "rank": "",
  "remarks": "PASS",
  "schoolName": "Sushma Patil Primary Vidyalaya, Kamothe",
  "score11": "24",
  "score12": "54",
  "score21": "32",
  "score22": "50",
  "remarks11": "PASS",
  "remarks12": "PASS",
  "remarks21": "PASS",
  "remarks22": "PASS",
  "status": "CHECKED",
  "rankSeq": "0",
  "award": "",
  "examCentreName": "Maji Amdar Dattusheth Patil Vidyalay, Kamothe (DSP SCHOOL)"
}