{
  "id": "673c2f7a87b872bfc",
  "name": "HAQUE SHIFA ANWARULL SEEMAPARWEEN from Guruvarya Balaram Patil Prathamik Vidyalay, Darave",
  "surname": "HAQUE",
  "firstName": "SHIFA",
  "fathersName": "ANWARULL",
  "mothersName": "SEEMAPARWEEN",
  "standard": "4",
  "medium": "Semi",
  "gender": "Female",
  "code": "4S1412010080",
  "barcode": "4S1412010080",
  "score": "86",
  "rank": "",
  "remarks": "PASS",
  "schoolName": "Guruvarya Balaram Patil Prathamik Vidyalay, Darave",
  "score11": "14",
  "score12": "22",
  "score21": "16",
  "score22": "34",
  "remarks11": "PASS",
  "remarks12": "FAIL",
  "remarks21": "PASS",
  "remarks22": "PASS",
  "status": "CHECKED",
  "rankSeq": "0",
  "award": "",
  "examCentreName": "Maji Amdar Dattusheth Patil Vidyalay, Kamothe (DSP SCHOOL)"
}