{
  "id": "672c62751e8ae1acb",
  "name": "SURATE SUPRIYA SUNIL POONAM from Takshashila Vidyalay, Ulhasnagar",
  "surname": "SURATE",
  "firstName": "SUPRIYA",
  "fathersName": "SUNIL",
  "mothersName": "POONAM",
  "standard": "4",
  "medium": "Semi",
  "gender": "Female",
  "code": "4S1515010097",
  "barcode": "4S1515010097",
  "score": "24",
  "rank": "",
  "remarks": "FAIL",
  "schoolName": "Takshashila Vidyalay, Ulhasnagar",
  "score11": "4",
  "score12": "0",
  "score21": "16",
  "score22": "4",
  "remarks11": "FAIL",
  "remarks12": "FAIL",
  "remarks21": "PASS",
  "remarks22": "FAIL",
  "status": "CHECKED",
  "rankSeq": "0",
  "award": "",
  "examCentreName": "Century Rayon Primary School, Shahad"
}