{
  "id": "6728ce7b4e8ea3e4c",
  "name": "PATIL PRATIK YOGESH ANITA from Z.P. School BegharsHome, Virar",
  "surname": "PATIL",
  "firstName": "PRATIK",
  "fathersName": "YOGESH",
  "mothersName": "ANITA",
  "standard": "4",
  "medium": "Semi",
  "gender": "Male",
  "code": "4S1605020106",
  "barcode": "4S1605020106",
  "score": "98",
  "rank": "",
  "remarks": "PASS",
  "schoolName": "Z.P. School BegharsHome, Virar",
  "score11": "20",
  "score12": "30",
  "score21": "22",
  "score22": "26",
  "remarks11": "PASS",
  "remarks12": "PASS",
  "remarks21": "PASS",
  "remarks22": "PASS",
  "status": "CHECKED",
  "rankSeq": "0",
  "award": "",
  "examCentreName": "AVA Education Society's NGV English Medium High School, Virar"
}