{
  "id": "673c3710da8514ad4",
  "name": "CHORGE OVI PRASHANT TEJESHRI from J.M. Rathi English School, Roha",
  "surname": "CHORGE",
  "firstName": "OVI",
  "fathersName": "PRASHANT",
  "mothersName": "TEJESHRI",
  "standard": "6",
  "medium": "English",
  "gender": "Female",
  "code": "6E1404010005",
  "barcode": "6E1404010005",
  "score": "170",
  "rank": "",
  "remarks": "PASS",
  "schoolName": "J.M. Rathi English School, Roha",
  "score11": "30",
  "score12": "38",
  "score21": "38",
  "score22": "64",
  "remarks11": "PASS",
  "remarks12": "PASS",
  "remarks21": "PASS",
  "remarks22": "PASS",
  "status": "CHECKED",
  "rankSeq": "0",
  "award": "",
  "examCentreName": "M.B. Patil English School, Roha"
}