{
  "id": "6728ce79b0eef5137",
  "name": "KAMAT SATWIK KRISHNA DIVYA from Smt. Taramai Vartak Memorial Academy, Virar",
  "surname": "KAMAT",
  "firstName": "SATWIK",
  "fathersName": "KRISHNA",
  "mothersName": "DIVYA",
  "standard": "6",
  "medium": "English",
  "gender": "Male",
  "code": "6E1605020008",
  "barcode": "6E1605020008",
  "score": "200",
  "rank": "",
  "remarks": "PASS",
  "schoolName": "Smt. Taramai Vartak Memorial Academy, Virar",
  "score11": "46",
  "score12": "80",
  "score21": "24",
  "score22": "50",
  "remarks11": "PASS",
  "remarks12": "PASS",
  "remarks21": "PASS",
  "remarks22": "PASS",
  "status": "CHECKED",
  "rankSeq": "0",
  "award": "",
  "examCentreName": "AVA Education Society's NGV English Medium High School, Virar"
}