{
  "id": "6731d63f64bff455b",
  "name": "GADHAGE TANVI GANESH - from Dasharath Arjun Bata Madyamik Vidyalaya, Vikhroli",
  "surname": "GADHAGE",
  "firstName": "TANVI",
  "fathersName": "GANESH",
  "mothersName": "'-",
  "standard": "6",
  "medium": "Semi",
  "gender": "Female",
  "code": "6S1303020078",
  "barcode": "6S1303020078",
  "score": "98",
  "rank": "",
  "remarks": "PASS",
  "schoolName": "Dasharath Arjun Bata Madyamik Vidyalaya, Vikhroli",
  "score11": "22",
  "score12": "38",
  "score21": "18",
  "score22": "20",
  "remarks11": "PASS",
  "remarks12": "PASS",
  "remarks21": "PASS",
  "remarks22": "FAIL",
  "status": "CHECKED",
  "rankSeq": "0",
  "award": "",
  "examCentreName": "Kamal Vasudev Vaykole English School, Vikhroli"
}