{
  "id": "673ed38904f63b162",
  "name": "BHANGADE ADVAY SACHIN JAYASHREE from Ram Bhau Bhise Balvikas Mandir, Nilje Dombivali",
  "surname": "BHANGADE",
  "firstName": "ADVAY",
  "fathersName": "SACHIN",
  "mothersName": "JAYASHREE",
  "standard": "6",
  "medium": "Semi",
  "gender": "Male",
  "code": "6S1516010024",
  "barcode": "6S1516010024",
  "score": "134",
  "rank": "",
  "remarks": "PASS",
  "schoolName": "Ram Bhau Bhise Balvikas Mandir, Nilje Dombivali",
  "score11": "28",
  "score12": "38",
  "score21": "20",
  "score22": "48",
  "remarks11": "PASS",
  "remarks12": "PASS",
  "remarks21": "PASS",
  "remarks22": "PASS",
  "status": "CHECKED",
  "rankSeq": "0",
  "award": "",
  "examCentreName": "Anna Saheb Pawar English School, Kalyan"
}