{
  "id": "672c627469e7b3bf0",
  "name": "GHODAKE KIRTI PRAVIN SUREKHA from Saraswati Vidyalay & Jr. College, Vasind",
  "surname": "GHODAKE",
  "firstName": "KIRTI",
  "fathersName": "PRAVIN",
  "mothersName": "SUREKHA",
  "standard": "6",
  "medium": "Semi",
  "gender": "Female",
  "code": "6S1512010078",
  "barcode": "6S1512010078",
  "score": "132",
  "rank": "",
  "remarks": "PASS",
  "schoolName": "Saraswati Vidyalay & Jr. College, Vasind",
  "score11": "30",
  "score12": "24",
  "score21": "24",
  "score22": "54",
  "remarks11": "PASS",
  "remarks12": "PASS",
  "remarks21": "PASS",
  "remarks22": "PASS",
  "status": "CHECKED",
  "rankSeq": "0",
  "award": "",
  "examCentreName": "New Ideal School & Jr. College, Vasind"
}