{
  "id": "672b506fc29fa8fab",
  "name": "JADHAV KAVERI SURENDRA DAMINI from H.H.C.P High School, Pune",
  "surname": "JADHAV",
  "firstName": "KAVERI",
  "fathersName": "SURENDRA",
  "mothersName": "DAMINI",
  "standard": "6",
  "medium": "Semi",
  "gender": "Female",
  "code": "6S2101010067",
  "barcode": "6S2101010067",
  "score": "194",
  "rank": "",
  "remarks": "PASS",
  "schoolName": "H.H.C.P High School, Pune",
  "score11": "32",
  "score12": "58",
  "score21": "38",
  "score22": "66",
  "remarks11": "PASS",
  "remarks12": "PASS",
  "remarks21": "PASS",
  "remarks22": "PASS",
  "status": "CHECKED",
  "rankSeq": "0",
  "award": "",
  "examCentreName": "S.S. Agarwal English Medium School, Pune"
}