{
  "id": "67333767c43cf2933",
  "name": "PALAV SAHIL GIRISH PRADNYA from Holy Cross High School, Kurla",
  "surname": "PALAV",
  "firstName": "SAHIL",
  "fathersName": "GIRISH",
  "mothersName": "PRADNYA",
  "standard": "7",
  "medium": "English",
  "gender": "Male",
  "code": "7E1305010009",
  "barcode": "7E1305010009",
  "score": "144",
  "rank": "",
  "remarks": "PASS",
  "schoolName": "Holy Cross High School, Kurla",
  "score11": "30",
  "score12": "36",
  "score21": "38",
  "score22": "40",
  "remarks11": "PASS",
  "remarks12": "PASS",
  "remarks21": "PASS",
  "remarks22": "PASS",
  "status": "CHECKED",
  "rankSeq": "0",
  "award": "",
  "examCentreName": "Gandhi Bal Mandir, Kurla"
}