{
  "id": "673c2f81a6e215b35",
  "name": "CHERPHALE TANMAY SANTOSH SHALAKA from Changu Kana Thakur Vidyalay Sec. Section, New Panvel",
  "surname": "CHERPHALE",
  "firstName": "TANMAY",
  "fathersName": "SANTOSH",
  "mothersName": "SHALAKA",
  "standard": "7",
  "medium": "English",
  "gender": "Male",
  "code": "7E1402010004",
  "barcode": "7E1402010004",
  "score": "160",
  "rank": "",
  "remarks": "PASS",
  "schoolName": "Changu Kana Thakur Vidyalay Sec. Section, New Panvel",
  "score11": "32",
  "score12": "44",
  "score21": "34",
  "score22": "50",
  "remarks11": "PASS",
  "remarks12": "PASS",
  "remarks21": "PASS",
  "remarks22": "PASS",
  "status": "CHECKED",
  "rankSeq": "0",
  "award": "",
  "examCentreName": "K.E.S.I.A.W. English Medium School, Panvel"
}