{
  "id": "6728ce6f176b7b435",
  "name": "KHANDAGALE JEET RAMAKANT RITU from National English School, Kudus",
  "surname": "KHANDAGALE",
  "firstName": "JEET",
  "fathersName": "RAMAKANT",
  "mothersName": "RITU",
  "standard": "7",
  "medium": "English",
  "gender": "Male",
  "code": "7E1604010017",
  "barcode": "7E1604010017",
  "score": "110",
  "rank": "",
  "remarks": "PASS",
  "schoolName": "National English School, Kudus",
  "score11": "18",
  "score12": "34",
  "score21": "16",
  "score22": "42",
  "remarks11": "PASS",
  "remarks12": "PASS",
  "remarks21": "PASS",
  "remarks22": "PASS",
  "status": "CHECKED",
  "rankSeq": "0",
  "award": "",
  "examCentreName": "National English School, Kudus"
}