{
  "id": "673c2f313c7b5989a",
  "name": "NIWATE SHRUTIKA RAMESH REVATI from Shree Ganesh Vidyamandir, Diva",
  "surname": "NIWATE",
  "firstName": "SHRUTIKA",
  "fathersName": "RAMESH",
  "mothersName": "REVATI",
  "standard": "7",
  "medium": "Marathi",
  "gender": "Female",
  "code": "7M1513010019",
  "barcode": "7M1513010019",
  "score": "144",
  "rank": "",
  "remarks": "PASS",
  "schoolName": "Shree Ganesh Vidyamandir, Diva",
  "score11": "32",
  "score12": "38",
  "score21": "26",
  "score22": "48",
  "remarks11": "PASS",
  "remarks12": "PASS",
  "remarks21": "PASS",
  "remarks22": "PASS",
  "status": "CHECKED",
  "rankSeq": "0",
  "award": "",
  "examCentreName": "Shree Ganesh Vidyamandir, Diva"
}