{
  "id": "6728ceb233135ff8e",
  "name": "HODAGE GATIK SANJAY ASHWINI from New English School, Nool",
  "surname": "HODAGE",
  "firstName": "GATIK",
  "fathersName": "SANJAY",
  "mothersName": "ASHWINI",
  "standard": "7",
  "medium": "Marathi",
  "gender": "Male",
  "code": "7M4101020092",
  "barcode": "7M4101020092",
  "score": "112",
  "rank": "",
  "remarks": "PASS",
  "schoolName": "New English School, Nool",
  "score11": "26",
  "score12": "32",
  "score21": "20",
  "score22": "34",
  "remarks11": "PASS",
  "remarks12": "PASS",
  "remarks21": "PASS",
  "remarks22": "PASS",
  "status": "CHECKED",
  "rankSeq": "0",
  "award": "",
  "examCentreName": "Shivraj College (Ground Floor), Gadhinglaj"
}