{
  "id": "6728ceb7b9d4fdbe5",
  "name": "JADHAV BHARGAV BHARAT SHARADA from Sau. V.D. Shinde High School, Gadhinglaj",
  "surname": "JADHAV",
  "firstName": "BHARGAV",
  "fathersName": "BHARAT",
  "mothersName": "SHARADA",
  "standard": "7",
  "medium": "Marathi",
  "gender": "Male",
  "code": "7M4101020100",
  "barcode": "7M4101020100",
  "score": "176",
  "rank": "",
  "remarks": "PASS",
  "schoolName": "Sau. V.D. Shinde High School, Gadhinglaj",
  "score11": "28",
  "score12": "58",
  "score21": "30",
  "score22": "60",
  "remarks11": "PASS",
  "remarks12": "PASS",
  "remarks21": "PASS",
  "remarks22": "PASS",
  "status": "CHECKED",
  "rankSeq": "0",
  "award": "",
  "examCentreName": "Shivraj College (Ground Floor), Gadhinglaj"
}