{
  "id": "673ed34d9e6110bc6",
  "name": "EBHAD PRANALI DEEPAK BHARTI from Sanmitra Mandal Vidya Mandir, Goregaon",
  "surname": "EBHAD",
  "firstName": "PRANALI",
  "fathersName": "DEEPAK",
  "mothersName": "BHARTI",
  "standard": "7",
  "medium": "Semi",
  "gender": "Female",
  "code": "7S1202010019",
  "barcode": "7S1202010019",
  "score": "142",
  "rank": "",
  "remarks": "PASS",
  "schoolName": "Sanmitra Mandal Vidya Mandir, Goregaon",
  "score11": "30",
  "score12": "40",
  "score21": "34",
  "score22": "38",
  "remarks11": "PASS",
  "remarks12": "PASS",
  "remarks21": "PASS",
  "remarks22": "PASS",
  "status": "CHECKED",
  "rankSeq": "0",
  "award": "",
  "examCentreName": "J.E.S. English School, Jogeshwari"
}