{
  "id": "6735e3e22a924ce98",
  "name": "MARATHE DARSHAN CHETANKUMAR VAISHALI from Sanket Vidyalay, Thane",
  "surname": "MARATHE",
  "firstName": "DARSHAN",
  "fathersName": "CHETANKUMAR",
  "mothersName": "VAISHALI",
  "standard": "7",
  "medium": "Semi",
  "gender": "Male",
  "code": "7S1505020034",
  "barcode": "7S1505020034",
  "score": "160",
  "rank": "",
  "remarks": "PASS",
  "schoolName": "Sanket Vidyalay, Thane",
  "score11": "32",
  "score12": "58",
  "score21": "28",
  "score22": "42",
  "remarks11": "PASS",
  "remarks12": "PASS",
  "remarks21": "PASS",
  "remarks22": "PASS",
  "status": "CHECKED",
  "rankSeq": "0",
  "award": "",
  "examCentreName": "Sanket Vidyalay, Thane"
}